{
  "users": [
    {
      "id": 1,
      "name": "Leanne Graham",
      "email": "Sincere@april.biz",
      "phone": "1-770-736-8031"
    },
    {
      "id": 2,
      "name": "Ervin Howell",
      "email": "Shanna@melissa.tv",
      "phone": "010-692-6593"
    },
    {
      "id": 3,
      "name": "Clementine Bauch",
      "email": "Nathan@yesenia.net",
      "phone": "1-463-123-4447"
    }
  ],
  "posts": [
    {
      "id": 1,
      "title": "First Post",
      "body": "This is the first post content",
      "userId": 1
    },
    {
      "id": 2,
      "title": "Second Post",
      "body": "This is the second post content",
      "userId": 2
    }
  ]
}